{
  "$schema": "https://schemas.wp.org/trunk/block.json",
  "apiVersion": 3,
  "name": "dch-block/teams",
  "title": "DCH Teams",
  "category": "dch-blocks",
  "keywords": [
    "teams",
    "teams block"
  ],
  "attributes": {
    "postsToShow": {
      "type": "number",
      "default": -1
    },
    "order": {
      "type": "string",
      "default": "DESC"
    },
    "orderBy": {
      "type": "string",
      "default": "title"
    }
  },
  "editorScript": "file:./index.js",
  "render": "file:./render.php"
}